Spartan/__init__.py
Spartan/spartan.py
Spartan/test.py
Spartan/lib/__init__.py
Spartan/lib/new_script.py
Spartan/lib/nmap-services
Spartan/lib/objects.py
Spartan/lib/packet.py
Spartan/lib/port_scan.py
Spartan/lib/scanner.py
Spartan/lib/script_execute.py
Spartan/lib/helpers/__init__.py
Spartan/lib/helpers/bruteforce_async.py
Spartan/lib/helpers/cms_detector.py
Spartan/lib/helpers/helpers.py
Spartan/scripts/ftp_info.py
Spartan/scripts/geoloc.py
Spartan/scripts/mysql_info.py
Spartan/scripts/ssh_info.py
Spartan/scripts/ssl_info.py
Spartan/scripts/test.py
fun/__init__.py
helpers/__init__.py
helpers/bruteforce_async.py
helpers/cms_detector.py
helpers/helpers.py
lib/__init__.py
lib/new_script.py
lib/nmap-services
lib/objects.py
lib/packet.py
lib/port_scan.py
lib/scanner.py
lib/script_execute.py
lib/helpers/__init__.py
lib/helpers/bruteforce_async.py
lib/helpers/cms_detector.py
lib/helpers/helpers.py
scripts/ftp_info.py
scripts/geoloc.py
scripts/mysql_info.py
scripts/ssh_info.py
scripts/ssl_info.py
scripts/test.py
spartan_scan-2.0.1.dist-info/LICENSE
spartan_scan-2.0.1.dist-info/METADATA
spartan_scan-2.0.1.dist-info/WHEEL
spartan_scan-2.0.1.dist-info/entry_points.txt
spartan_scan-2.0.1.dist-info/top_level.txt
spartan_scan-2.0.1.dist-info/RECORD
