Metadata-Version: 2.1
Name: spartan-scan
Version: 2.0.1
Summary: TCP/IP port scanner
Author-email: WaletLab <kontakt@waletlab.com>
Maintainer-email: WaletLab <kontakt@waletlab.com>
Project-URL: Repository, https://github.com/WaletLab/Spartan.git
Project-URL: Issues, https://github.com/WaletLab/Spartan/issues
Keywords: port scan,port,networking,security
Classifier: Development Status :: 5 - Production/Stable
Classifier: Intended Audience :: Developers
Classifier: Intended Audience :: Information Technology
Classifier: Topic :: Internet
Classifier: Topic :: Security
Classifier: License :: OSI Approved :: GNU General Public License v3 (GPLv3)
Classifier: Programming Language :: Python :: 3
Classifier: Programming Language :: Python :: 3.10
Classifier: Programming Language :: Python :: 3.11
Classifier: Programming Language :: Python :: 3.12
Requires-Python: >=3.10
License-File: LICENSE
Requires-Dist: rich>=13.7.1
Requires-Dist: art>=6.2
Requires-Dist: scapy>=2.5.0
Requires-Dist: requests>=2.32.2
Requires-Dist: typer>=0.12.3
